GoogleSheetsLibrary/__init__.py
rf_googlesheetslibrary-0.2.dist-info/LICENSE
rf_googlesheetslibrary-0.2.dist-info/METADATA
rf_googlesheetslibrary-0.2.dist-info/WHEEL
rf_googlesheetslibrary-0.2.dist-info/top_level.txt
rf_googlesheetslibrary-0.2.dist-info/RECORD
