Metadata-Version: 2.1
Name: rf-googlesheetslibrary
Version: 0.2
Summary: Test Library for interfacing tests with Google Sheets API v4
Home-page: https://github.com/MainSystemDev/GoogleSheetsLibrary
Author: Joshua Kim Rivera
Author-email: joshua.rivera@mnltechnology.com
License: Type license() to see the full license text
Platform: any
Classifier: Development Status :: 5 - Production/Stable
Classifier: License :: OSI Approved :: MIT License
Classifier: Operating System :: OS Independent
Classifier: Programming Language :: Python :: 3 :: Only
Classifier: Topic :: Software Development :: Testing
Classifier: Framework :: Robot Framework
Classifier: Framework :: Robot Framework :: Library
Requires-Dist: google-api-python-client
Requires-Dist: google-auth-httplib2
Requires-Dist: google-auth-oauthlib
Requires-Dist: google-auth
Requires-Dist: oauth2client
Requires-Dist: robotframework (>=4.0.3)
Requires-Dist: robotframework-pythonlibcore (>=3.0.0)
